[
  [
    {
      "id": "19873909",
      "title": "免佣）近捷運東湖【超值電梯】有廚房★警衛管理★垃圾代收",
      "link": "https://rent.591.com.tw/19873909"
    },
    {
      "id": "19873905",
      "title": "葫洲❣可租補報稅/獨洗曬/採光通風/衛浴開窗/傢俱齊全",
      "link": "https://rent.591.com.tw/19873905"
    },
    {
      "id": "19816819",
      "title": "東湖生活圈*東湖樂高挑高大套房",
      "link": "https://rent.591.com.tw/19816819"
    },
    {
      "id": "19872899",
      "title": "大湖公園-全新裝潢-近捷運-可租補-可寵-可開伙-拎包入住",
      "link": "https://rent.591.com.tw/19872899"
    },
    {
      "id": "19872827",
      "title": "近捷運東湖【超值電梯】有廚房★警衛管理★垃圾代收",
      "link": "https://rent.591.com.tw/19872827"
    },
    {
      "id": "19872607",
      "title": "捷運東湖／電梯租案。採光強。機優。可炊煮",
      "link": "https://rent.591.com.tw/19872607"
    },
    {
      "id": "19872500",
      "title": "軟體園區站、低樓層、小資首選、收垃圾、機能強",
      "link": "https://rent.591.com.tw/19872500"
    },
    {
      "id": "6714027",
      "title": "福德二路全新傢俱套房",
      "link": "https://rent.591.com.tw/6714027"
    },
    {
      "id": "19787379",
      "title": "近東湖國中／小資套房。新裝潢。機能優",
      "link": "https://rent.591.com.tw/19787379"
    },
    {
      "id": "19799708",
      "title": "近東湖國中／小資套房。新裝潢。機能優",
      "link": "https://rent.591.com.tw/19799708"
    },
    {
      "id": "19839210",
      "title": "捷運東湖／超值租案。獨立洗衣。凸窗曬衣。變頻冷氣。飲水機",
      "link": "https://rent.591.com.tw/19839210"
    },
    {
      "id": "19799656",
      "title": "捷運東湖、康樂商圈／超值套房。獨立洗衣。變頻冷氣。採光佳",
      "link": "https://rent.591.com.tw/19799656"
    },
    {
      "id": "19470178",
      "title": "近捷運內湖／採光套房。變頻冷氣。天然瓦斯。飲水機。台電價",
      "link": "https://rent.591.com.tw/19470178"
    },
    {
      "id": "19590430",
      "title": "捷運東湖／採光套房。獨立洗衣。流理台。可補助",
      "link": "https://rent.591.com.tw/19590430"
    },
    {
      "id": "19805226",
      "title": "飯店式管理住的安心也放心，一天不用$650",
      "link": "https://rent.591.com.tw/19805226"
    }
  ],
  [
    {
      "id": "19874118",
      "title": "後山埤、陽台、新整理、可寵",
      "link": "https://rent.591.com.tw/19874118"
    },
    {
      "id": "19874002",
      "title": "小巨蛋、電梯管理、收垃圾、機能好",
      "link": "https://rent.591.com.tw/19874002"
    },
    {
      "id": "19873982",
      "title": "松山、獨洗、對外窗、可貓、採光",
      "link": "https://rent.591.com.tw/19873982"
    },
    {
      "id": "19873949",
      "title": "251A大雅房、短租月租、租補、垃圾代收、近象山站101",
      "link": "https://rent.591.com.tw/19873949"
    },
    {
      "id": "19873909",
      "title": "免佣）近捷運東湖【超值電梯】有廚房★警衛管理★垃圾代收",
      "link": "https://rent.591.com.tw/19873909"
    },
    {
      "id": "19873905",
      "title": "葫洲❣可租補報稅/獨洗曬/採光通風/衛浴開窗/傢俱齊全",
      "link": "https://rent.591.com.tw/19873905"
    },
    {
      "id": "19873888",
      "title": "市府、獨洗、陽台、天然瓦斯、台電計價",
      "link": "https://rent.591.com.tw/19873888"
    },
    {
      "id": "19873854",
      "title": "象山、可貓、對外窗、垃圾代收、獨洗",
      "link": "https://rent.591.com.tw/19873854"
    },
    {
      "id": "19873829",
      "title": "永春、流理台、靜巷、獨洗、對外窗",
      "link": "https://rent.591.com.tw/19873829"
    },
    {
      "id": "19873745",
      "title": "昆陽正對面/飲水機/採光佳/機能強/小資首選/稀有釋出",
      "link": "https://rent.591.com.tw/19873745"
    },
    {
      "id": "19873716",
      "title": "後山埤/獨洗/飲水機/走道窗/機能強/新裝潢/採光佳/稀有",
      "link": "https://rent.591.com.tw/19873716"
    },
    {
      "id": "19816819",
      "title": "東湖生活圈*東湖樂高挑高大套房",
      "link": "https://rent.591.com.tw/19816819"
    },
    {
      "id": "19872827",
      "title": "近捷運東湖【超值電梯】有廚房★警衛管理★垃圾代收",
      "link": "https://rent.591.com.tw/19872827"
    },
    {
      "id": "19872607",
      "title": "捷運東湖／電梯租案。採光強。機優。可炊煮",
      "link": "https://rent.591.com.tw/19872607"
    },
    {
      "id": "19872500",
      "title": "軟體園區站、低樓層、小資首選、收垃圾、機能強",
      "link": "https://rent.591.com.tw/19872500"
    }
  ]
]